[
  {
    "job_id": null,
    "title": "Asia Program Manager",
    "company": "NGO Recruitment",
    "location": "Jakarta, Indonesia",
    "link": "https://id.linkedin.com/jobs/view/asia-program-manager-at-ngo-recruitment-4323242126",
    "salary_info": null,
    "benefits": null,
    "search_role": "ngo",
    "search_filters": {
      "job_type": "F",
      "experience": "4",
      "date_filter": "r2592000"
    },
    "posted_time": "2025-11-19",
    "job_type": "Full-time",
    "experience_level": "Mid-Senior Level",
    "work_arrangement": "Not Specified",
    "scraped_at": "2025-12-02T19:56:25.154243",
    "metadata": {
      "is_remote": false,
      "is_internship": false,
      "is_part_time": false,
      "is_freelance": false,
      "is_fresh_graduate": false,
      "keywords": [
        "manager"
      ]
    }
  },
  {
    "job_id": null,
    "title": "Grant & Financial Management Specialist (Project Bengo/Project Marine)",
    "company": "WWF Indonesia",
    "location": "Jakarta, Indonesia",
    "link": "https://id.linkedin.com/jobs/view/grant-financial-management-specialist-project-bengo-project-marine-at-wwf-indonesia-4323073178",
    "salary_info": null,
    "benefits": null,
    "search_role": "ngo",
    "search_filters": {
      "job_type": "F",
      "experience": "4",
      "date_filter": "r2592000"
    },
    "posted_time": "2025-11-18",
    "job_type": "Full-time",
    "experience_level": "Mid-Senior Level",
    "work_arrangement": "Not Specified",
    "scraped_at": "2025-12-02T19:56:25.154555",
    "metadata": {
      "is_remote": false,
      "is_internship": false,
      "is_part_time": false,
      "is_freelance": false,
      "is_fresh_graduate": false,
      "keywords": [
        "specialist"
      ]
    }
  },
  {
    "job_id": null,
    "title": "Outreach and External Communications Manager",
    "company": "Yayasan Plan International Indonesia",
    "location": "Jakarta, Indonesia",
    "link": "https://id.linkedin.com/jobs/view/outreach-and-external-communications-manager-at-yayasan-plan-international-indonesia-4334286301",
    "salary_info": null,
    "benefits": null,
    "search_role": "ngo",
    "search_filters": {
      "job_type": "F",
      "experience": "4",
      "date_filter": "r2592000"
    },
    "posted_time": "2025-11-05",
    "job_type": "Full-time",
    "experience_level": "Mid-Senior Level",
    "work_arrangement": "Not Specified",
    "scraped_at": "2025-12-02T19:56:25.154879",
    "metadata": {
      "is_remote": false,
      "is_internship": false,
      "is_part_time": false,
      "is_freelance": false,
      "is_fresh_graduate": false,
      "keywords": [
        "manager"
      ]
    }
  },
  {
    "job_id": null,
    "title": "Admin & Finance Officer - NTT",
    "company": "DT Global",
    "location": "Jakarta, Jakarta, Indonesia",
    "link": "https://id.linkedin.com/jobs/view/admin-finance-officer-ntt-at-dt-global-4323682618",
    "salary_info": null,
    "benefits": null,
    "search_role": "ngo",
    "search_filters": {
      "job_type": "F",
      "experience": "4",
      "date_filter": "r2592000"
    },
    "posted_time": "2025-11-20",
    "job_type": "Full-time",
    "experience_level": "Mid-Senior Level",
    "work_arrangement": "Not Specified",
    "scraped_at": "2025-12-02T19:56:25.155200",
    "metadata": {
      "is_remote": false,
      "is_internship": false,
      "is_part_time": false,
      "is_freelance": false,
      "is_fresh_graduate": false,
      "keywords": [
        "officer"
      ]
    }
  },
  {
    "job_id": null,
    "title": "Infectious Disease Surveillance Advisor, Global Health Programs (GHP), STRIDES",
    "company": "PATH",
    "location": "Jakarta Metropolitan Area",
    "link": "https://id.linkedin.com/jobs/view/infectious-disease-surveillance-advisor-global-health-programs-ghp-strides-at-path-4339119531",
    "salary_info": null,
    "benefits": null,
    "search_role": "ngo",
    "search_filters": {
      "job_type": "F",
      "experience": "4",
      "date_filter": "r2592000"
    },
    "posted_time": "2025-11-26",
    "job_type": "Full-time",
    "experience_level": "Mid-Senior Level",
    "work_arrangement": "Not Specified",
    "scraped_at": "2025-12-02T19:56:25.155489",
    "metadata": {
      "is_remote": false,
      "is_internship": false,
      "is_part_time": false,
      "is_freelance": false,
      "is_fresh_graduate": false,
      "keywords": []
    }
  },
  {
    "job_id": null,
    "title": "Stakeholder Relations Manager",
    "company": "Multi Bintang Indonesia",
    "location": "Surabaya, East Java, Indonesia",
    "link": "https://id.linkedin.com/jobs/view/stakeholder-relations-manager-at-multi-bintang-indonesia-4308170896",
    "salary_info": null,
    "benefits": null,
    "search_role": "ngo",
    "search_filters": {
      "job_type": "F",
      "experience": "4",
      "date_filter": "r2592000"
    },
    "posted_time": "2025-11-12",
    "job_type": "Full-time",
    "experience_level": "Mid-Senior Level",
    "work_arrangement": "Not Specified",
    "scraped_at": "2025-12-02T19:56:25.155809",
    "metadata": {
      "is_remote": false,
      "is_internship": false,
      "is_part_time": false,
      "is_freelance": false,
      "is_fresh_graduate": false,
      "keywords": [
        "manager"
      ]
    }
  },
  {
    "job_id": null,
    "title": "Senior Specialist, Advisory Services, Southeast Asia",
    "company": "Women's World Banking",
    "location": "Jakarta, Indonesia",
    "link": "https://id.linkedin.com/jobs/view/senior-specialist-advisory-services-southeast-asia-at-women-s-world-banking-4333963109",
    "salary_info": null,
    "benefits": null,
    "search_role": "ngo",
    "search_filters": {
      "job_type": "F",
      "experience": "4",
      "date_filter": "r2592000"
    },
    "posted_time": "2025-11-04",
    "job_type": "Full-time",
    "experience_level": "Mid-Senior Level",
    "work_arrangement": "Not Specified",
    "scraped_at": "2025-12-02T19:56:25.156098",
    "metadata": {
      "is_remote": false,
      "is_internship": false,
      "is_part_time": false,
      "is_freelance": false,
      "is_fresh_graduate": false,
      "keywords": [
        "specialist",
        "senior"
      ]
    }
  },
  {
    "job_id": null,
    "title": "District Lead-East Nusa Tenggara",
    "company": "STIR Education",
    "location": "Kupang, East Nusa Tenggara, Indonesia",
    "link": "https://id.linkedin.com/jobs/view/district-lead-east-nusa-tenggara-at-stir-education-4321828697",
    "salary_info": null,
    "benefits": null,
    "search_role": "ngo",
    "search_filters": {
      "job_type": "F",
      "experience": "4",
      "date_filter": "r2592000"
    },
    "posted_time": "2025-11-12",
    "job_type": "Full-time",
    "experience_level": "Mid-Senior Level",
    "work_arrangement": "Not Specified",
    "scraped_at": "2025-12-02T19:56:25.156388",
    "metadata": {
      "is_remote": false,
      "is_internship": false,
      "is_part_time": false,
      "is_freelance": false,
      "is_fresh_graduate": false,
      "keywords": [
        "lead"
      ]
    }
  },
  {
    "job_id": null,
    "title": "Finance & Operations Manager",
    "company": "Jhpiego",
    "location": "South Sulawesi, Indonesia",
    "link": "https://id.linkedin.com/jobs/view/finance-operations-manager-at-jhpiego-4333979731",
    "salary_info": null,
    "benefits": null,
    "search_role": "ngo",
    "search_filters": {
      "job_type": "F",
      "experience": "4",
      "date_filter": "r2592000"
    },
    "posted_time": "2025-11-07",
    "job_type": "Full-time",
    "experience_level": "Mid-Senior Level",
    "work_arrangement": "Not Specified",
    "scraped_at": "2025-12-02T19:56:25.156703",
    "metadata": {
      "is_remote": false,
      "is_internship": false,
      "is_part_time": false,
      "is_freelance": false,
      "is_fresh_graduate": false,
      "keywords": [
        "manager"
      ]
    }
  },
  {
    "job_id": null,
    "title": "Desktop Services Administrator",
    "company": "Speedcast",
    "location": "Kecamatan Cimahi Selatan, West Java, Indonesia",
    "link": "https://id.linkedin.com/jobs/view/desktop-services-administrator-at-speedcast-4267762847",
    "salary_info": null,
    "benefits": null,
    "search_role": "ngo",
    "search_filters": {
      "job_type": "F",
      "experience": "4",
      "date_filter": "r2592000"
    },
    "posted_time": "2025-11-24",
    "job_type": "Full-time",
    "experience_level": "Mid-Senior Level",
    "work_arrangement": "Not Specified",
    "scraped_at": "2025-12-02T19:56:25.156992",
    "metadata": {
      "is_remote": false,
      "is_internship": false,
      "is_part_time": false,
      "is_freelance": false,
      "is_fresh_graduate": false,
      "keywords": [
        "administrator"
      ]
    }
  },
  {
    "job_id": null,
    "title": "Fundraising Associate Intern",
    "company": "Infectious Disease Alliance",
    "location": "Jakarta Metropolitan Area",
    "link": "https://id.linkedin.com/jobs/view/fundraising-associate-intern-at-infectious-disease-alliance-4348051628",
    "salary_info": null,
    "benefits": null,
    "search_role": "ngo",
    "search_filters": {
      "job_type": "I",
      "experience": "1",
      "date_filter": "r2592000"
    },
    "posted_time": "2025-12-01",
    "job_type": "Internship",
    "experience_level": "Internship",
    "work_arrangement": "Not Specified",
    "scraped_at": "2025-12-02T19:57:01.132152",
    "metadata": {
      "is_remote": false,
      "is_internship": true,
      "is_part_time": false,
      "is_freelance": false,
      "is_fresh_graduate": false,
      "keywords": []
    }
  },
  {
    "job_id": null,
    "title": "Operations Director, Indonesia",
    "company": "Wildlife Conservation Society",
    "location": "Bogor, West Java, Indonesia",
    "link": "https://id.linkedin.com/jobs/view/operations-director-indonesia-at-wildlife-conservation-society-4335331536",
    "salary_info": null,
    "benefits": null,
    "search_role": "ngo",
    "search_filters": {
      "remote": "R",
      "date_filter": "r604800"
    },
    "posted_time": "2025-12-02",
    "job_type": "Unknown",
    "experience_level": "Manager/Director",
    "work_arrangement": "Remote",
    "scraped_at": "2025-12-02T19:57:39.577576",
    "metadata": {
      "is_remote": false,
      "is_internship": false,
      "is_part_time": false,
      "is_freelance": false,
      "is_fresh_graduate": false,
      "keywords": [
        "director"
      ]
    }
  },
  {
    "job_id": null,
    "title": "Industrial Relation Senior Manager",
    "company": "DHL Supply Chain",
    "location": "Jakarta, Jakarta, Indonesia",
    "link": "https://id.linkedin.com/jobs/view/industrial-relation-senior-manager-at-dhl-supply-chain-4323518806",
    "salary_info": null,
    "benefits": null,
    "search_role": "ngo",
    "search_filters": {
      "remote": "R",
      "date_filter": "r604800"
    },
    "posted_time": "2025-12-01",
    "job_type": "Unknown",
    "experience_level": "Senior",
    "work_arrangement": "Remote",
    "scraped_at": "2025-12-02T19:57:39.578083",
    "metadata": {
      "is_remote": false,
      "is_internship": false,
      "is_part_time": false,
      "is_freelance": false,
      "is_fresh_graduate": false,
      "keywords": [
        "manager",
        "senior"
      ]
    }
  },
  {
    "job_id": null,
    "title": "Chinese Teacher",
    "company": "Cetta Online Class",
    "location": "Jakarta, Indonesia",
    "link": "https://id.linkedin.com/jobs/view/chinese-teacher-at-cetta-online-class-4223690610",
    "salary_info": null,
    "benefits": null,
    "search_role": "ngo",
    "search_filters": {
      "remote": "R",
      "date_filter": "r604800"
    },
    "posted_time": "2025-12-01",
    "job_type": "Unknown",
    "experience_level": "Not Specified",
    "work_arrangement": "Remote",
    "scraped_at": "2025-12-02T19:57:39.579072",
    "metadata": {
      "is_remote": false,
      "is_internship": false,
      "is_part_time": false,
      "is_freelance": false,
      "is_fresh_graduate": false,
      "keywords": []
    }
  },
  {
    "job_id": null,
    "title": "Part Time Japanese Tutor",
    "company": "Cetta Online Class",
    "location": "Indonesia",
    "link": "https://id.linkedin.com/jobs/view/part-time-japanese-tutor-at-cetta-online-class-4325105601",
    "salary_info": null,
    "benefits": null,
    "search_role": "ngo",
    "search_filters": {
      "remote": "R",
      "date_filter": "r604800"
    },
    "posted_time": "2025-12-01",
    "job_type": "Part-time",
    "experience_level": "Not Specified",
    "work_arrangement": "Remote",
    "scraped_at": "2025-12-02T19:57:39.579641",
    "metadata": {
      "is_remote": false,
      "is_internship": false,
      "is_part_time": true,
      "is_freelance": false,
      "is_fresh_graduate": false,
      "keywords": []
    }
  }
]